heyexReader/__init__.py
heyexReader/volReader.py
reader/__init__.py
reader/test.py
heyexReader-0.1.3.dist-info/LICENSE
heyexReader-0.1.3.dist-info/METADATA
heyexReader-0.1.3.dist-info/WHEEL
heyexReader-0.1.3.dist-info/top_level.txt
heyexReader-0.1.3.dist-info/RECORD
